{
    "name": "template",
    "namePlural": "templates",

    "frontend": true,

    "traits": [],

    "fields": [],

    "fillables": [],
    "casts": {},

    "allowedSorts": [],
    "allowedEmbeds": [],
    "allowedFields": [],

    "relationshipFields": [
        {
            "title": "",
            "field": "",
            "model": "",
            "relationship": "",
            "fieldType": "",
            "url": "",
            "relationshipType": ""
        }
    ],

    "hasOne": [],
    "belongsTo": [],
    "belongsToMany": [],
    "hasMany": [],
    "hasOneThrough": [],
    "hasManyThrough": [],

    "morphMany": {},
    "morphToMany": {},
    "morphTo": [],
    "morphOne": [],
    "morphedByMany": [],

    "seeder": 10,

    "revisionModel": null
}
